{
	"workflow_runs_stats_summary": {
		"total_runs_count": 36,
		"name": "Merge",
		"rate": {
			"success_rate": 0.8333333333333334,
			"failure_rate": 0.16666666666666666,
			"others_rate": -2.7755575615628914e-17
		},
		"execution_duration_stats": {
			"min": 1991,
			"max": 3278,
			"avg": 2354.5333333333333,
			"med": 2307,
			"std": 289.49746496683224
		},
		"conclusions": {
			"failure": {
				"runs_count": 6,
				"workflow_runs": [
					{
						"id": 15633930601,
						"status": "completed",
						"conclusion": "failure",
						"actor": "tgummerer",
						"run_attempt": 1,
						"html_url": "https://github.com/pulumi/pulumi/actions/runs/15633930601/attempts/1",
						"jobs_url": "https://api.github.com/repos/pulumi/pulumi/actions/runs/15633930601/jobs",
						"logs_url": "https://api.github.com/repos/pulumi/pulumi/actions/runs/15633930601/logs",
						"run_started_at": "2025-06-13T11:54:46Z",
						"update_at": "2025-06-13T12:28:02Z",
						"created_at": "2025-06-13T11:54:46Z",
						"duration": 1996
					},
					{
						"id": 15620535123,
						"status": "completed",
						"conclusion": "failure",
						"actor": "Frassle",
						"run_attempt": 1,
						"html_url": "https://github.com/pulumi/pulumi/actions/runs/15620535123/attempts/1",
						"jobs_url": "https://api.github.com/repos/pulumi/pulumi/actions/runs/15620535123/jobs",
						"logs_url": "https://api.github.com/repos/pulumi/pulumi/actions/runs/15620535123/logs",
						"run_started_at": "2025-06-12T20:50:40Z",
						"update_at": "2025-06-12T21:12:28Z",
						"created_at": "2025-06-12T20:50:40Z",
						"duration": 1308
					},
					{
						"id": 15617448360,
						"status": "completed",
						"conclusion": "failure",
						"actor": "Frassle",
						"run_attempt": 1,
						"html_url": "https://github.com/pulumi/pulumi/actions/runs/15617448360/attempts/1",
						"jobs_url": "https://api.github.com/repos/pulumi/pulumi/actions/runs/15617448360/jobs",
						"logs_url": "https://api.github.com/repos/pulumi/pulumi/actions/runs/15617448360/logs",
						"run_started_at": "2025-06-12T17:42:05Z",
						"update_at": "2025-06-12T18:59:33Z",
						"created_at": "2025-06-12T17:42:05Z",
						"duration": 4648
					},
					{
						"id": 15606742695,
						"status": "completed",
						"conclusion": "failure",
						"actor": "tgummerer",
						"run_attempt": 1,
						"html_url": "https://github.com/pulumi/pulumi/actions/runs/15606742695/attempts/1",
						"jobs_url": "https://api.github.com/repos/pulumi/pulumi/actions/runs/15606742695/jobs",
						"logs_url": "https://api.github.com/repos/pulumi/pulumi/actions/runs/15606742695/logs",
						"run_started_at": "2025-06-12T09:24:07Z",
						"update_at": "2025-06-12T10:21:18Z",
						"created_at": "2025-06-12T09:24:07Z",
						"duration": 3431
					},
					{
						"id": 15586043121,
						"status": "completed",
						"conclusion": "failure",
						"actor": "julienp",
						"run_attempt": 1,
						"html_url": "https://github.com/pulumi/pulumi/actions/runs/15586043121/attempts/1",
						"jobs_url": "https://api.github.com/repos/pulumi/pulumi/actions/runs/15586043121/jobs",
						"logs_url": "https://api.github.com/repos/pulumi/pulumi/actions/runs/15586043121/logs",
						"run_started_at": "2025-06-11T13:21:04Z",
						"update_at": "2025-06-11T14:03:52Z",
						"created_at": "2025-06-11T13:21:04Z",
						"duration": 2568
					},
					{
						"id": 15582258730,
						"status": "completed",
						"conclusion": "failure",
						"actor": "tgummerer",
						"run_attempt": 1,
						"html_url": "https://github.com/pulumi/pulumi/actions/runs/15582258730/attempts/1",
						"jobs_url": "https://api.github.com/repos/pulumi/pulumi/actions/runs/15582258730/jobs",
						"logs_url": "https://api.github.com/repos/pulumi/pulumi/actions/runs/15582258730/logs",
						"run_started_at": "2025-06-11T10:18:36Z",
						"update_at": "2025-06-11T11:06:34Z",
						"created_at": "2025-06-11T10:18:36Z",
						"duration": 2878
					}
				]
			},
			"others": {
				"runs_count": 0,
				"workflow_runs": []
			},
			"success": {
				"runs_count": 30,
				"workflow_runs": [
					{
						"id": 15634375051,
						"status": "completed",
						"conclusion": "success",
						"actor": "pulumi-bot",
						"run_attempt": 1,
						"html_url": "https://github.com/pulumi/pulumi/actions/runs/15634375051/attempts/1",
						"jobs_url": "https://api.github.com/repos/pulumi/pulumi/actions/runs/15634375051/jobs",
						"logs_url": "https://api.github.com/repos/pulumi/pulumi/actions/runs/15634375051/logs",
						"run_started_at": "2025-06-13T12:19:17Z",
						"update_at": "2025-06-13T12:56:04Z",
						"created_at": "2025-06-13T12:19:17Z",
						"duration": 2207
					},
					{
						"id": 15631670777,
						"status": "completed",
						"conclusion": "success",
						"actor": "tgummerer",
						"run_attempt": 1,
						"html_url": "https://github.com/pulumi/pulumi/actions/runs/15631670777/attempts/1",
						"jobs_url": "https://api.github.com/repos/pulumi/pulumi/actions/runs/15631670777/jobs",
						"logs_url": "https://api.github.com/repos/pulumi/pulumi/actions/runs/15631670777/logs",
						"run_started_at": "2025-06-13T09:49:09Z",
						"update_at": "2025-06-13T10:26:06Z",
						"created_at": "2025-06-13T09:49:09Z",
						"duration": 2217
					},
					{
						"id": 15630890117,
						"status": "completed",
						"conclusion": "success",
						"actor": "Frassle",
						"run_attempt": 1,
						"html_url": "https://github.com/pulumi/pulumi/actions/runs/15630890117/attempts/1",
						"jobs_url": "https://api.github.com/repos/pulumi/pulumi/actions/runs/15630890117/jobs",
						"logs_url": "https://api.github.com/repos/pulumi/pulumi/actions/runs/15630890117/logs",
						"run_started_at": "2025-06-13T09:08:52Z",
						"update_at": "2025-06-13T09:42:35Z",
						"created_at": "2025-06-13T09:08:52Z",
						"duration": 2023
					},
					{
						"id": 15630752110,
						"status": "completed",
						"conclusion": "success",
						"actor": "tgummerer",
						"run_attempt": 1,
						"html_url": "https://github.com/pulumi/pulumi/actions/runs/15630752110/attempts/1",
						"jobs_url": "https://api.github.com/repos/pulumi/pulumi/actions/runs/15630752110/jobs",
						"logs_url": "https://api.github.com/repos/pulumi/pulumi/actions/runs/15630752110/logs",
						"run_started_at": "2025-06-13T09:02:04Z",
						"update_at": "2025-06-13T09:35:15Z",
						"created_at": "2025-06-13T09:02:04Z",
						"duration": 1991
					},
					{
						"id": 15629947725,
						"status": "completed",
						"conclusion": "success",
						"actor": "lunaris",
						"run_attempt": 1,
						"html_url": "https://github.com/pulumi/pulumi/actions/runs/15629947725/attempts/1",
						"jobs_url": "https://api.github.com/repos/pulumi/pulumi/actions/runs/15629947725/jobs",
						"logs_url": "https://api.github.com/repos/pulumi/pulumi/actions/runs/15629947725/logs",
						"run_started_at": "2025-06-13T08:20:31Z",
						"update_at": "2025-06-13T08:55:24Z",
						"created_at": "2025-06-13T08:20:31Z",
						"duration": 2093
					},
					{
						"id": 15629285851,
						"status": "completed",
						"conclusion": "success",
						"actor": "tgummerer",
						"run_attempt": 1,
						"html_url": "https://github.com/pulumi/pulumi/actions/runs/15629285851/attempts/1",
						"jobs_url": "https://api.github.com/repos/pulumi/pulumi/actions/runs/15629285851/jobs",
						"logs_url": "https://api.github.com/repos/pulumi/pulumi/actions/runs/15629285851/logs",
						"run_started_at": "2025-06-13T07:44:00Z",
						"update_at": "2025-06-13T08:19:11Z",
						"created_at": "2025-06-13T07:44:00Z",
						"duration": 2111
					},
					{
						"id": 15620969330,
						"status": "completed",
						"conclusion": "success",
						"actor": "Frassle",
						"run_attempt": 1,
						"html_url": "https://github.com/pulumi/pulumi/actions/runs/15620969330/attempts/1",
						"jobs_url": "https://api.github.com/repos/pulumi/pulumi/actions/runs/15620969330/jobs",
						"logs_url": "https://api.github.com/repos/pulumi/pulumi/actions/runs/15620969330/logs",
						"run_started_at": "2025-06-12T21:16:24Z",
						"update_at": "2025-06-12T21:50:52Z",
						"created_at": "2025-06-12T21:16:24Z",
						"duration": 2068
					},
					{
						"id": 15614419308,
						"status": "completed",
						"conclusion": "success",
						"actor": "tgummerer",
						"run_attempt": 1,
						"html_url": "https://github.com/pulumi/pulumi/actions/runs/15614419308/attempts/1",
						"jobs_url": "https://api.github.com/repos/pulumi/pulumi/actions/runs/15614419308/jobs",
						"logs_url": "https://api.github.com/repos/pulumi/pulumi/actions/runs/15614419308/logs",
						"run_started_at": "2025-06-12T15:13:51Z",
						"update_at": "2025-06-12T15:50:46Z",
						"created_at": "2025-06-12T15:13:51Z",
						"duration": 2215
					},
					{
						"id": 15613122064,
						"status": "completed",
						"conclusion": "success",
						"actor": "Frassle",
						"run_attempt": 1,
						"html_url": "https://github.com/pulumi/pulumi/actions/runs/15613122064/attempts/1",
						"jobs_url": "https://api.github.com/repos/pulumi/pulumi/actions/runs/15613122064/jobs",
						"logs_url": "https://api.github.com/repos/pulumi/pulumi/actions/runs/15613122064/logs",
						"run_started_at": "2025-06-12T14:19:41Z",
						"update_at": "2025-06-12T14:58:30Z",
						"created_at": "2025-06-12T14:19:41Z",
						"duration": 2329
					},
					{
						"id": 15612420616,
						"status": "completed",
						"conclusion": "success",
						"actor": "tgummerer",
						"run_attempt": 1,
						"html_url": "https://github.com/pulumi/pulumi/actions/runs/15612420616/attempts/1",
						"jobs_url": "https://api.github.com/repos/pulumi/pulumi/actions/runs/15612420616/jobs",
						"logs_url": "https://api.github.com/repos/pulumi/pulumi/actions/runs/15612420616/logs",
						"run_started_at": "2025-06-12T13:50:56Z",
						"update_at": "2025-06-12T14:30:32Z",
						"created_at": "2025-06-12T13:50:56Z",
						"duration": 2376
					},
					{
						"id": 15611028610,
						"status": "completed",
						"conclusion": "success",
						"actor": "pulumi-bot",
						"run_attempt": 1,
						"html_url": "https://github.com/pulumi/pulumi/actions/runs/15611028610/attempts/1",
						"jobs_url": "https://api.github.com/repos/pulumi/pulumi/actions/runs/15611028610/jobs",
						"logs_url": "https://api.github.com/repos/pulumi/pulumi/actions/runs/15611028610/logs",
						"run_started_at": "2025-06-12T12:52:14Z",
						"update_at": "2025-06-12T13:31:23Z",
						"created_at": "2025-06-12T12:52:14Z",
						"duration": 2349
					},
					{
						"id": 15610330966,
						"status": "completed",
						"conclusion": "success",
						"actor": "julienp",
						"run_attempt": 1,
						"html_url": "https://github.com/pulumi/pulumi/actions/runs/15610330966/attempts/1",
						"jobs_url": "https://api.github.com/repos/pulumi/pulumi/actions/runs/15610330966/jobs",
						"logs_url": "https://api.github.com/repos/pulumi/pulumi/actions/runs/15610330966/logs",
						"run_started_at": "2025-06-12T12:20:27Z",
						"update_at": "2025-06-12T12:59:20Z",
						"created_at": "2025-06-12T12:20:27Z",
						"duration": 2333
					},
					{
						"id": 15607020714,
						"status": "completed",
						"conclusion": "success",
						"actor": "tgummerer",
						"run_attempt": 1,
						"html_url": "https://github.com/pulumi/pulumi/actions/runs/15607020714/attempts/1",
						"jobs_url": "https://api.github.com/repos/pulumi/pulumi/actions/runs/15607020714/jobs",
						"logs_url": "https://api.github.com/repos/pulumi/pulumi/actions/runs/15607020714/logs",
						"run_started_at": "2025-06-12T09:37:03Z",
						"update_at": "2025-06-12T10:15:29Z",
						"created_at": "2025-06-12T09:37:03Z",
						"duration": 2306
					},
					{
						"id": 15606087413,
						"status": "completed",
						"conclusion": "success",
						"actor": "tgummerer",
						"run_attempt": 1,
						"html_url": "https://github.com/pulumi/pulumi/actions/runs/15606087413/attempts/1",
						"jobs_url": "https://api.github.com/repos/pulumi/pulumi/actions/runs/15606087413/jobs",
						"logs_url": "https://api.github.com/repos/pulumi/pulumi/actions/runs/15606087413/logs",
						"run_started_at": "2025-06-12T08:54:00Z",
						"update_at": "2025-06-12T09:34:11Z",
						"created_at": "2025-06-12T08:54:00Z",
						"duration": 2411
					},
					{
						"id": 15605286457,
						"status": "completed",
						"conclusion": "success",
						"actor": "julienp",
						"run_attempt": 1,
						"html_url": "https://github.com/pulumi/pulumi/actions/runs/15605286457/attempts/1",
						"jobs_url": "https://api.github.com/repos/pulumi/pulumi/actions/runs/15605286457/jobs",
						"logs_url": "https://api.github.com/repos/pulumi/pulumi/actions/runs/15605286457/logs",
						"run_started_at": "2025-06-12T08:15:35Z",
						"update_at": "2025-06-12T08:53:35Z",
						"created_at": "2025-06-12T08:15:35Z",
						"duration": 2280
					},
					{
						"id": 15605262782,
						"status": "completed",
						"conclusion": "success",
						"actor": "tgummerer",
						"run_attempt": 1,
						"html_url": "https://github.com/pulumi/pulumi/actions/runs/15605262782/attempts/1",
						"jobs_url": "https://api.github.com/repos/pulumi/pulumi/actions/runs/15605262782/jobs",
						"logs_url": "https://api.github.com/repos/pulumi/pulumi/actions/runs/15605262782/logs",
						"run_started_at": "2025-06-12T08:14:26Z",
						"update_at": "2025-06-12T08:51:04Z",
						"created_at": "2025-06-12T08:14:26Z",
						"duration": 2198
					},
					{
						"id": 15604798024,
						"status": "completed",
						"conclusion": "success",
						"actor": "tgummerer",
						"run_attempt": 1,
						"html_url": "https://github.com/pulumi/pulumi/actions/runs/15604798024/attempts/1",
						"jobs_url": "https://api.github.com/repos/pulumi/pulumi/actions/runs/15604798024/jobs",
						"logs_url": "https://api.github.com/repos/pulumi/pulumi/actions/runs/15604798024/logs",
						"run_started_at": "2025-06-12T07:51:15Z",
						"update_at": "2025-06-12T08:29:38Z",
						"created_at": "2025-06-12T07:51:15Z",
						"duration": 2303
					},
					{
						"id": 15590939320,
						"status": "completed",
						"conclusion": "success",
						"actor": "Frassle",
						"run_attempt": 1,
						"html_url": "https://github.com/pulumi/pulumi/actions/runs/15590939320/attempts/1",
						"jobs_url": "https://api.github.com/repos/pulumi/pulumi/actions/runs/15590939320/jobs",
						"logs_url": "https://api.github.com/repos/pulumi/pulumi/actions/runs/15590939320/logs",
						"run_started_at": "2025-06-11T16:56:53Z",
						"update_at": "2025-06-11T17:40:22Z",
						"created_at": "2025-06-11T16:56:53Z",
						"duration": 2609
					},
					{
						"id": 15588727304,
						"status": "completed",
						"conclusion": "success",
						"actor": "tgummerer",
						"run_attempt": 1,
						"html_url": "https://github.com/pulumi/pulumi/actions/runs/15588727304/attempts/1",
						"jobs_url": "https://api.github.com/repos/pulumi/pulumi/actions/runs/15588727304/jobs",
						"logs_url": "https://api.github.com/repos/pulumi/pulumi/actions/runs/15588727304/logs",
						"run_started_at": "2025-06-11T15:11:50Z",
						"update_at": "2025-06-11T15:50:38Z",
						"created_at": "2025-06-11T15:11:50Z",
						"duration": 2328
					},
					{
						"id": 15583955907,
						"status": "completed",
						"conclusion": "success",
						"actor": "iwahbe",
						"run_attempt": 1,
						"html_url": "https://github.com/pulumi/pulumi/actions/runs/15583955907/attempts/1",
						"jobs_url": "https://api.github.com/repos/pulumi/pulumi/actions/runs/15583955907/jobs",
						"logs_url": "https://api.github.com/repos/pulumi/pulumi/actions/runs/15583955907/logs",
						"run_started_at": "2025-06-11T11:44:22Z",
						"update_at": "2025-06-11T12:21:49Z",
						"created_at": "2025-06-11T11:44:22Z",
						"duration": 2247
					},
					{
						"id": 15583487809,
						"status": "completed",
						"conclusion": "success",
						"actor": "tgummerer",
						"run_attempt": 1,
						"html_url": "https://github.com/pulumi/pulumi/actions/runs/15583487809/attempts/1",
						"jobs_url": "https://api.github.com/repos/pulumi/pulumi/actions/runs/15583487809/jobs",
						"logs_url": "https://api.github.com/repos/pulumi/pulumi/actions/runs/15583487809/logs",
						"run_started_at": "2025-06-11T11:20:56Z",
						"update_at": "2025-06-11T11:56:26Z",
						"created_at": "2025-06-11T11:20:56Z",
						"duration": 2130
					},
					{
						"id": 15582086691,
						"status": "completed",
						"conclusion": "success",
						"actor": "tgummerer",
						"run_attempt": 1,
						"html_url": "https://github.com/pulumi/pulumi/actions/runs/15582086691/attempts/1",
						"jobs_url": "https://api.github.com/repos/pulumi/pulumi/actions/runs/15582086691/jobs",
						"logs_url": "https://api.github.com/repos/pulumi/pulumi/actions/runs/15582086691/logs",
						"run_started_at": "2025-06-11T10:10:07Z",
						"update_at": "2025-06-11T10:45:46Z",
						"created_at": "2025-06-11T10:10:07Z",
						"duration": 2139
					},
					{
						"id": 15581307807,
						"status": "completed",
						"conclusion": "success",
						"actor": "iwahbe",
						"run_attempt": 1,
						"html_url": "https://github.com/pulumi/pulumi/actions/runs/15581307807/attempts/1",
						"jobs_url": "https://api.github.com/repos/pulumi/pulumi/actions/runs/15581307807/jobs",
						"logs_url": "https://api.github.com/repos/pulumi/pulumi/actions/runs/15581307807/logs",
						"run_started_at": "2025-06-11T09:32:40Z",
						"update_at": "2025-06-11T10:13:58Z",
						"created_at": "2025-06-11T09:32:40Z",
						"duration": 2478
					},
					{
						"id": 15577750782,
						"status": "completed",
						"conclusion": "success",
						"actor": "justinvp",
						"run_attempt": 1,
						"html_url": "https://github.com/pulumi/pulumi/actions/runs/15577750782/attempts/1",
						"jobs_url": "https://api.github.com/repos/pulumi/pulumi/actions/runs/15577750782/jobs",
						"logs_url": "https://api.github.com/repos/pulumi/pulumi/actions/runs/15577750782/logs",
						"run_started_at": "2025-06-11T06:33:17Z",
						"update_at": "2025-06-11T07:11:45Z",
						"created_at": "2025-06-11T06:33:17Z",
						"duration": 2308
					},
					{
						"id": 15563266243,
						"status": "completed",
						"conclusion": "success",
						"actor": "julienp",
						"run_attempt": 1,
						"html_url": "https://github.com/pulumi/pulumi/actions/runs/15563266243/attempts/1",
						"jobs_url": "https://api.github.com/repos/pulumi/pulumi/actions/runs/15563266243/jobs",
						"logs_url": "https://api.github.com/repos/pulumi/pulumi/actions/runs/15563266243/logs",
						"run_started_at": "2025-06-10T15:09:00Z",
						"update_at": "2025-06-10T15:58:25Z",
						"created_at": "2025-06-10T15:09:00Z",
						"duration": 2965
					},
					{
						"id": 15554335116,
						"status": "completed",
						"conclusion": "success",
						"actor": "tgummerer",
						"run_attempt": 1,
						"html_url": "https://github.com/pulumi/pulumi/actions/runs/15554335116/attempts/1",
						"jobs_url": "https://api.github.com/repos/pulumi/pulumi/actions/runs/15554335116/jobs",
						"logs_url": "https://api.github.com/repos/pulumi/pulumi/actions/runs/15554335116/logs",
						"run_started_at": "2025-06-10T08:20:27Z",
						"update_at": "2025-06-10T09:11:44Z",
						"created_at": "2025-06-10T08:20:27Z",
						"duration": 3077
					},
					{
						"id": 15545059760,
						"status": "completed",
						"conclusion": "success",
						"actor": "Frassle",
						"run_attempt": 1,
						"html_url": "https://github.com/pulumi/pulumi/actions/runs/15545059760/attempts/1",
						"jobs_url": "https://api.github.com/repos/pulumi/pulumi/actions/runs/15545059760/jobs",
						"logs_url": "https://api.github.com/repos/pulumi/pulumi/actions/runs/15545059760/logs",
						"run_started_at": "2025-06-09T21:30:28Z",
						"update_at": "2025-06-09T22:25:06Z",
						"created_at": "2025-06-09T21:30:28Z",
						"duration": 3278
					},
					{
						"id": 15534931967,
						"status": "completed",
						"conclusion": "success",
						"actor": "Frassle",
						"run_attempt": 1,
						"html_url": "https://github.com/pulumi/pulumi/actions/runs/15534931967/attempts/1",
						"jobs_url": "https://api.github.com/repos/pulumi/pulumi/actions/runs/15534931967/jobs",
						"logs_url": "https://api.github.com/repos/pulumi/pulumi/actions/runs/15534931967/logs",
						"run_started_at": "2025-06-09T12:48:45Z",
						"update_at": "2025-06-09T13:30:28Z",
						"created_at": "2025-06-09T12:48:45Z",
						"duration": 2503
					},
					{
						"id": 15534833622,
						"status": "completed",
						"conclusion": "success",
						"actor": "lunaris",
						"run_attempt": 1,
						"html_url": "https://github.com/pulumi/pulumi/actions/runs/15534833622/attempts/1",
						"jobs_url": "https://api.github.com/repos/pulumi/pulumi/actions/runs/15534833622/jobs",
						"logs_url": "https://api.github.com/repos/pulumi/pulumi/actions/runs/15534833622/logs",
						"run_started_at": "2025-06-09T12:43:50Z",
						"update_at": "2025-06-09T13:23:25Z",
						"created_at": "2025-06-09T12:43:50Z",
						"duration": 2375
					},
					{
						"id": 15530087776,
						"status": "completed",
						"conclusion": "success",
						"actor": "Frassle",
						"run_attempt": 1,
						"html_url": "https://github.com/pulumi/pulumi/actions/runs/15530087776/attempts/1",
						"jobs_url": "https://api.github.com/repos/pulumi/pulumi/actions/runs/15530087776/jobs",
						"logs_url": "https://api.github.com/repos/pulumi/pulumi/actions/runs/15530087776/logs",
						"run_started_at": "2025-06-09T08:19:18Z",
						"update_at": "2025-06-09T08:59:07Z",
						"created_at": "2025-06-09T08:19:18Z",
						"duration": 2389
					}
				]
			}
		}
	},
	"workflow_jobs_stats_summary": []
}
