{
	"workflow_runs_stats_summary": {
		"total_runs_count": 35,
		"name": "Merge",
		"rate": {
			"success_rate": 0.8285714285714286,
			"failure_rate": 0.14285714285714285,
			"others_rate": 0.028571428571428525
		},
		"execution_duration_stats": {
			"min": 2856,
			"max": 4502,
			"avg": 3117.206896551724,
			"med": 3001,
			"std": 378.33504393550294
		},
		"conclusions": {
			"failure": {
				"runs_count": 5,
				"workflow_runs": [
					{
						"id": 20753305605,
						"status": "completed",
						"conclusion": "failure",
						"actor": "julienp",
						"run_attempt": 1,
						"html_url": "https://github.com/pulumi/pulumi/actions/runs/20753305605/attempts/1",
						"jobs_url": "https://api.github.com/repos/pulumi/pulumi/actions/runs/20753305605/jobs",
						"logs_url": "https://api.github.com/repos/pulumi/pulumi/actions/runs/20753305605/logs",
						"run_started_at": "2026-01-06T15:37:43Z",
						"update_at": "2026-01-06T16:24:26Z",
						"created_at": "2026-01-06T15:37:43Z",
						"duration": 2803
					},
					{
						"id": 20718049758,
						"status": "completed",
						"conclusion": "failure",
						"actor": "julienp",
						"run_attempt": 1,
						"html_url": "https://github.com/pulumi/pulumi/actions/runs/20718049758/attempts/1",
						"jobs_url": "https://api.github.com/repos/pulumi/pulumi/actions/runs/20718049758/jobs",
						"logs_url": "https://api.github.com/repos/pulumi/pulumi/actions/runs/20718049758/logs",
						"run_started_at": "2026-01-05T14:12:32Z",
						"update_at": "2026-01-05T14:43:06Z",
						"created_at": "2026-01-05T14:12:32Z",
						"duration": 1834
					},
					{
						"id": 20710090985,
						"status": "completed",
						"conclusion": "failure",
						"actor": "tgummerer",
						"run_attempt": 1,
						"html_url": "https://github.com/pulumi/pulumi/actions/runs/20710090985/attempts/1",
						"jobs_url": "https://api.github.com/repos/pulumi/pulumi/actions/runs/20710090985/jobs",
						"logs_url": "https://api.github.com/repos/pulumi/pulumi/actions/runs/20710090985/logs",
						"run_started_at": "2026-01-05T08:55:34Z",
						"update_at": "2026-01-05T09:31:08Z",
						"created_at": "2026-01-05T08:55:34Z",
						"duration": 2134
					},
					{
						"id": 20674194766,
						"status": "completed",
						"conclusion": "failure",
						"actor": "iwahbe",
						"run_attempt": 1,
						"html_url": "https://github.com/pulumi/pulumi/actions/runs/20674194766/attempts/1",
						"jobs_url": "https://api.github.com/repos/pulumi/pulumi/actions/runs/20674194766/jobs",
						"logs_url": "https://api.github.com/repos/pulumi/pulumi/actions/runs/20674194766/logs",
						"run_started_at": "2026-01-03T07:29:33Z",
						"update_at": "2026-01-03T08:09:49Z",
						"created_at": "2026-01-03T07:29:33Z",
						"duration": 2416
					},
					{
						"id": 20670355115,
						"status": "completed",
						"conclusion": "failure",
						"actor": "iwahbe",
						"run_attempt": 1,
						"html_url": "https://github.com/pulumi/pulumi/actions/runs/20670355115/attempts/1",
						"jobs_url": "https://api.github.com/repos/pulumi/pulumi/actions/runs/20670355115/jobs",
						"logs_url": "https://api.github.com/repos/pulumi/pulumi/actions/runs/20670355115/logs",
						"run_started_at": "2026-01-03T01:34:18Z",
						"update_at": "2026-01-03T02:27:49Z",
						"created_at": "2026-01-03T01:34:18Z",
						"duration": 3211
					}
				]
			},
			"others": {
				"runs_count": 1,
				"workflow_runs": [
					{
						"id": 20777662354,
						"status": "completed",
						"conclusion": "cancelled",
						"actor": "julienp",
						"run_attempt": 1,
						"html_url": "https://github.com/pulumi/pulumi/actions/runs/20777662354/attempts/1",
						"jobs_url": "https://api.github.com/repos/pulumi/pulumi/actions/runs/20777662354/jobs",
						"logs_url": "https://api.github.com/repos/pulumi/pulumi/actions/runs/20777662354/logs",
						"run_started_at": "2026-01-07T10:01:27Z",
						"update_at": "2026-01-07T11:14:49Z",
						"created_at": "2026-01-07T10:01:27Z",
						"duration": 4402
					}
				]
			},
			"success": {
				"runs_count": 29,
				"workflow_runs": [
					{
						"id": 20793596483,
						"status": "completed",
						"conclusion": "success",
						"actor": "pulumi-bot",
						"run_attempt": 1,
						"html_url": "https://github.com/pulumi/pulumi/actions/runs/20793596483/attempts/1",
						"jobs_url": "https://api.github.com/repos/pulumi/pulumi/actions/runs/20793596483/jobs",
						"logs_url": "https://api.github.com/repos/pulumi/pulumi/actions/runs/20793596483/logs",
						"run_started_at": "2026-01-07T19:17:09Z",
						"update_at": "2026-01-07T20:27:41Z",
						"created_at": "2026-01-07T19:17:09Z",
						"duration": 4232
					},
					{
						"id": 20788206730,
						"status": "completed",
						"conclusion": "success",
						"actor": "tgummerer",
						"run_attempt": 1,
						"html_url": "https://github.com/pulumi/pulumi/actions/runs/20788206730/attempts/1",
						"jobs_url": "https://api.github.com/repos/pulumi/pulumi/actions/runs/20788206730/jobs",
						"logs_url": "https://api.github.com/repos/pulumi/pulumi/actions/runs/20788206730/logs",
						"run_started_at": "2026-01-07T16:20:04Z",
						"update_at": "2026-01-07T17:09:24Z",
						"created_at": "2026-01-07T16:20:04Z",
						"duration": 2960
					},
					{
						"id": 20787954157,
						"status": "completed",
						"conclusion": "success",
						"actor": "julienp",
						"run_attempt": 1,
						"html_url": "https://github.com/pulumi/pulumi/actions/runs/20787954157/attempts/1",
						"jobs_url": "https://api.github.com/repos/pulumi/pulumi/actions/runs/20787954157/jobs",
						"logs_url": "https://api.github.com/repos/pulumi/pulumi/actions/runs/20787954157/logs",
						"run_started_at": "2026-01-07T16:12:11Z",
						"update_at": "2026-01-07T17:02:27Z",
						"created_at": "2026-01-07T16:12:11Z",
						"duration": 3016
					},
					{
						"id": 20787762555,
						"status": "completed",
						"conclusion": "success",
						"actor": "julienp",
						"run_attempt": 1,
						"html_url": "https://github.com/pulumi/pulumi/actions/runs/20787762555/attempts/1",
						"jobs_url": "https://api.github.com/repos/pulumi/pulumi/actions/runs/20787762555/jobs",
						"logs_url": "https://api.github.com/repos/pulumi/pulumi/actions/runs/20787762555/logs",
						"run_started_at": "2026-01-07T16:06:19Z",
						"update_at": "2026-01-07T16:56:33Z",
						"created_at": "2026-01-07T16:06:19Z",
						"duration": 3014
					},
					{
						"id": 20783535121,
						"status": "completed",
						"conclusion": "success",
						"actor": "tgummerer",
						"run_attempt": 1,
						"html_url": "https://github.com/pulumi/pulumi/actions/runs/20783535121/attempts/1",
						"jobs_url": "https://api.github.com/repos/pulumi/pulumi/actions/runs/20783535121/jobs",
						"logs_url": "https://api.github.com/repos/pulumi/pulumi/actions/runs/20783535121/logs",
						"run_started_at": "2026-01-07T13:44:52Z",
						"update_at": "2026-01-07T14:35:29Z",
						"created_at": "2026-01-07T13:44:52Z",
						"duration": 3037
					},
					{
						"id": 20781386586,
						"status": "completed",
						"conclusion": "success",
						"actor": "tgummerer",
						"run_attempt": 1,
						"html_url": "https://github.com/pulumi/pulumi/actions/runs/20781386586/attempts/1",
						"jobs_url": "https://api.github.com/repos/pulumi/pulumi/actions/runs/20781386586/jobs",
						"logs_url": "https://api.github.com/repos/pulumi/pulumi/actions/runs/20781386586/logs",
						"run_started_at": "2026-01-07T12:24:22Z",
						"update_at": "2026-01-07T13:13:10Z",
						"created_at": "2026-01-07T12:24:22Z",
						"duration": 2928
					},
					{
						"id": 20779746943,
						"status": "completed",
						"conclusion": "success",
						"actor": "julienp",
						"run_attempt": 1,
						"html_url": "https://github.com/pulumi/pulumi/actions/runs/20779746943/attempts/1",
						"jobs_url": "https://api.github.com/repos/pulumi/pulumi/actions/runs/20779746943/jobs",
						"logs_url": "https://api.github.com/repos/pulumi/pulumi/actions/runs/20779746943/logs",
						"run_started_at": "2026-01-07T11:19:45Z",
						"update_at": "2026-01-07T12:08:17Z",
						"created_at": "2026-01-07T11:19:45Z",
						"duration": 2912
					},
					{
						"id": 20757319874,
						"status": "completed",
						"conclusion": "success",
						"actor": "julienp",
						"run_attempt": 1,
						"html_url": "https://github.com/pulumi/pulumi/actions/runs/20757319874/attempts/1",
						"jobs_url": "https://api.github.com/repos/pulumi/pulumi/actions/runs/20757319874/jobs",
						"logs_url": "https://api.github.com/repos/pulumi/pulumi/actions/runs/20757319874/logs",
						"run_started_at": "2026-01-06T18:02:52Z",
						"update_at": "2026-01-06T18:52:55Z",
						"created_at": "2026-01-06T18:02:52Z",
						"duration": 3003
					},
					{
						"id": 20731513977,
						"status": "completed",
						"conclusion": "success",
						"actor": "iwahbe",
						"run_attempt": 1,
						"html_url": "https://github.com/pulumi/pulumi/actions/runs/20731513977/attempts/1",
						"jobs_url": "https://api.github.com/repos/pulumi/pulumi/actions/runs/20731513977/jobs",
						"logs_url": "https://api.github.com/repos/pulumi/pulumi/actions/runs/20731513977/logs",
						"run_started_at": "2026-01-05T22:45:57Z",
						"update_at": "2026-01-05T23:34:40Z",
						"created_at": "2026-01-05T22:45:57Z",
						"duration": 2923
					},
					{
						"id": 20729527752,
						"status": "completed",
						"conclusion": "success",
						"actor": "joeduffy",
						"run_attempt": 1,
						"html_url": "https://github.com/pulumi/pulumi/actions/runs/20729527752/attempts/1",
						"jobs_url": "https://api.github.com/repos/pulumi/pulumi/actions/runs/20729527752/jobs",
						"logs_url": "https://api.github.com/repos/pulumi/pulumi/actions/runs/20729527752/logs",
						"run_started_at": "2026-01-05T21:21:23Z",
						"update_at": "2026-01-05T22:15:03Z",
						"created_at": "2026-01-05T21:21:23Z",
						"duration": 3220
					},
					{
						"id": 20723719029,
						"status": "completed",
						"conclusion": "success",
						"actor": "julienp",
						"run_attempt": 1,
						"html_url": "https://github.com/pulumi/pulumi/actions/runs/20723719029/attempts/1",
						"jobs_url": "https://api.github.com/repos/pulumi/pulumi/actions/runs/20723719029/jobs",
						"logs_url": "https://api.github.com/repos/pulumi/pulumi/actions/runs/20723719029/logs",
						"run_started_at": "2026-01-05T17:33:53Z",
						"update_at": "2026-01-05T18:27:41Z",
						"created_at": "2026-01-05T17:33:53Z",
						"duration": 3228
					},
					{
						"id": 20722809449,
						"status": "completed",
						"conclusion": "success",
						"actor": "tgummerer",
						"run_attempt": 1,
						"html_url": "https://github.com/pulumi/pulumi/actions/runs/20722809449/attempts/1",
						"jobs_url": "https://api.github.com/repos/pulumi/pulumi/actions/runs/20722809449/jobs",
						"logs_url": "https://api.github.com/repos/pulumi/pulumi/actions/runs/20722809449/logs",
						"run_started_at": "2026-01-05T17:00:21Z",
						"update_at": "2026-01-05T17:49:02Z",
						"created_at": "2026-01-05T17:00:21Z",
						"duration": 2921
					},
					{
						"id": 20720380999,
						"status": "completed",
						"conclusion": "success",
						"actor": "julienp",
						"run_attempt": 1,
						"html_url": "https://github.com/pulumi/pulumi/actions/runs/20720380999/attempts/1",
						"jobs_url": "https://api.github.com/repos/pulumi/pulumi/actions/runs/20720380999/jobs",
						"logs_url": "https://api.github.com/repos/pulumi/pulumi/actions/runs/20720380999/logs",
						"run_started_at": "2026-01-05T15:34:22Z",
						"update_at": "2026-01-05T16:23:05Z",
						"created_at": "2026-01-05T15:34:22Z",
						"duration": 2923
					},
					{
						"id": 20719770665,
						"status": "completed",
						"conclusion": "success",
						"actor": "tgummerer",
						"run_attempt": 1,
						"html_url": "https://github.com/pulumi/pulumi/actions/runs/20719770665/attempts/1",
						"jobs_url": "https://api.github.com/repos/pulumi/pulumi/actions/runs/20719770665/jobs",
						"logs_url": "https://api.github.com/repos/pulumi/pulumi/actions/runs/20719770665/logs",
						"run_started_at": "2026-01-05T15:13:33Z",
						"update_at": "2026-01-05T16:04:36Z",
						"created_at": "2026-01-05T15:13:33Z",
						"duration": 3063
					},
					{
						"id": 20719139127,
						"status": "completed",
						"conclusion": "success",
						"actor": "tgummerer",
						"run_attempt": 1,
						"html_url": "https://github.com/pulumi/pulumi/actions/runs/20719139127/attempts/1",
						"jobs_url": "https://api.github.com/repos/pulumi/pulumi/actions/runs/20719139127/jobs",
						"logs_url": "https://api.github.com/repos/pulumi/pulumi/actions/runs/20719139127/logs",
						"run_started_at": "2026-01-05T14:51:50Z",
						"update_at": "2026-01-05T15:41:09Z",
						"created_at": "2026-01-05T14:51:50Z",
						"duration": 2959
					},
					{
						"id": 20717224972,
						"status": "completed",
						"conclusion": "success",
						"actor": "julienp",
						"run_attempt": 1,
						"html_url": "https://github.com/pulumi/pulumi/actions/runs/20717224972/attempts/1",
						"jobs_url": "https://api.github.com/repos/pulumi/pulumi/actions/runs/20717224972/jobs",
						"logs_url": "https://api.github.com/repos/pulumi/pulumi/actions/runs/20717224972/logs",
						"run_started_at": "2026-01-05T13:41:28Z",
						"update_at": "2026-01-05T14:31:12Z",
						"created_at": "2026-01-05T13:41:28Z",
						"duration": 2984
					},
					{
						"id": 20711729279,
						"status": "completed",
						"conclusion": "success",
						"actor": "tgummerer",
						"run_attempt": 1,
						"html_url": "https://github.com/pulumi/pulumi/actions/runs/20711729279/attempts/1",
						"jobs_url": "https://api.github.com/repos/pulumi/pulumi/actions/runs/20711729279/jobs",
						"logs_url": "https://api.github.com/repos/pulumi/pulumi/actions/runs/20711729279/logs",
						"run_started_at": "2026-01-05T09:59:02Z",
						"update_at": "2026-01-05T11:14:04Z",
						"created_at": "2026-01-05T09:59:02Z",
						"duration": 4502
					},
					{
						"id": 20711145156,
						"status": "completed",
						"conclusion": "success",
						"actor": "tgummerer",
						"run_attempt": 1,
						"html_url": "https://github.com/pulumi/pulumi/actions/runs/20711145156/attempts/1",
						"jobs_url": "https://api.github.com/repos/pulumi/pulumi/actions/runs/20711145156/jobs",
						"logs_url": "https://api.github.com/repos/pulumi/pulumi/actions/runs/20711145156/logs",
						"run_started_at": "2026-01-05T09:36:20Z",
						"update_at": "2026-01-05T10:26:08Z",
						"created_at": "2026-01-05T09:36:20Z",
						"duration": 2988
					},
					{
						"id": 20682374726,
						"status": "completed",
						"conclusion": "success",
						"actor": "pulumi-bot",
						"run_attempt": 1,
						"html_url": "https://github.com/pulumi/pulumi/actions/runs/20682374726/attempts/1",
						"jobs_url": "https://api.github.com/repos/pulumi/pulumi/actions/runs/20682374726/jobs",
						"logs_url": "https://api.github.com/repos/pulumi/pulumi/actions/runs/20682374726/logs",
						"run_started_at": "2026-01-03T20:15:14Z",
						"update_at": "2026-01-03T21:04:36Z",
						"created_at": "2026-01-03T20:15:14Z",
						"duration": 2962
					},
					{
						"id": 20675745852,
						"status": "completed",
						"conclusion": "success",
						"actor": "iwahbe",
						"run_attempt": 1,
						"html_url": "https://github.com/pulumi/pulumi/actions/runs/20675745852/attempts/1",
						"jobs_url": "https://api.github.com/repos/pulumi/pulumi/actions/runs/20675745852/jobs",
						"logs_url": "https://api.github.com/repos/pulumi/pulumi/actions/runs/20675745852/logs",
						"run_started_at": "2026-01-03T10:01:38Z",
						"update_at": "2026-01-03T10:49:21Z",
						"created_at": "2026-01-03T10:01:38Z",
						"duration": 2863
					},
					{
						"id": 20675529417,
						"status": "completed",
						"conclusion": "success",
						"actor": "iwahbe",
						"run_attempt": 1,
						"html_url": "https://github.com/pulumi/pulumi/actions/runs/20675529417/attempts/1",
						"jobs_url": "https://api.github.com/repos/pulumi/pulumi/actions/runs/20675529417/jobs",
						"logs_url": "https://api.github.com/repos/pulumi/pulumi/actions/runs/20675529417/logs",
						"run_started_at": "2026-01-03T09:38:45Z",
						"update_at": "2026-01-03T10:41:17Z",
						"created_at": "2026-01-03T09:38:45Z",
						"duration": 3752
					},
					{
						"id": 20674879578,
						"status": "completed",
						"conclusion": "success",
						"actor": "iwahbe",
						"run_attempt": 1,
						"html_url": "https://github.com/pulumi/pulumi/actions/runs/20674879578/attempts/1",
						"jobs_url": "https://api.github.com/repos/pulumi/pulumi/actions/runs/20674879578/jobs",
						"logs_url": "https://api.github.com/repos/pulumi/pulumi/actions/runs/20674879578/logs",
						"run_started_at": "2026-01-03T08:37:01Z",
						"update_at": "2026-01-03T09:24:37Z",
						"created_at": "2026-01-03T08:37:01Z",
						"duration": 2856
					},
					{
						"id": 20671361990,
						"status": "completed",
						"conclusion": "success",
						"actor": "iwahbe",
						"run_attempt": 1,
						"html_url": "https://github.com/pulumi/pulumi/actions/runs/20671361990/attempts/1",
						"jobs_url": "https://api.github.com/repos/pulumi/pulumi/actions/runs/20671361990/jobs",
						"logs_url": "https://api.github.com/repos/pulumi/pulumi/actions/runs/20671361990/logs",
						"run_started_at": "2026-01-03T03:05:05Z",
						"update_at": "2026-01-03T03:53:22Z",
						"created_at": "2026-01-03T03:05:05Z",
						"duration": 2897
					},
					{
						"id": 20668906599,
						"status": "completed",
						"conclusion": "success",
						"actor": "iwahbe",
						"run_attempt": 1,
						"html_url": "https://github.com/pulumi/pulumi/actions/runs/20668906599/attempts/1",
						"jobs_url": "https://api.github.com/repos/pulumi/pulumi/actions/runs/20668906599/jobs",
						"logs_url": "https://api.github.com/repos/pulumi/pulumi/actions/runs/20668906599/logs",
						"run_started_at": "2026-01-02T23:36:29Z",
						"update_at": "2026-01-03T00:26:30Z",
						"created_at": "2026-01-02T23:36:29Z",
						"duration": 3001
					},
					{
						"id": 20666060717,
						"status": "completed",
						"conclusion": "success",
						"actor": "iwahbe",
						"run_attempt": 1,
						"html_url": "https://github.com/pulumi/pulumi/actions/runs/20666060717/attempts/1",
						"jobs_url": "https://api.github.com/repos/pulumi/pulumi/actions/runs/20666060717/jobs",
						"logs_url": "https://api.github.com/repos/pulumi/pulumi/actions/runs/20666060717/logs",
						"run_started_at": "2026-01-02T20:25:56Z",
						"update_at": "2026-01-02T21:17:26Z",
						"created_at": "2026-01-02T20:25:56Z",
						"duration": 3090
					},
					{
						"id": 20660659808,
						"status": "completed",
						"conclusion": "success",
						"actor": "tgummerer",
						"run_attempt": 1,
						"html_url": "https://github.com/pulumi/pulumi/actions/runs/20660659808/attempts/1",
						"jobs_url": "https://api.github.com/repos/pulumi/pulumi/actions/runs/20660659808/jobs",
						"logs_url": "https://api.github.com/repos/pulumi/pulumi/actions/runs/20660659808/logs",
						"run_started_at": "2026-01-02T15:11:35Z",
						"update_at": "2026-01-02T16:02:15Z",
						"created_at": "2026-01-02T15:11:35Z",
						"duration": 3040
					},
					{
						"id": 20659263400,
						"status": "completed",
						"conclusion": "success",
						"actor": "i-am-tom",
						"run_attempt": 1,
						"html_url": "https://github.com/pulumi/pulumi/actions/runs/20659263400/attempts/1",
						"jobs_url": "https://api.github.com/repos/pulumi/pulumi/actions/runs/20659263400/jobs",
						"logs_url": "https://api.github.com/repos/pulumi/pulumi/actions/runs/20659263400/logs",
						"run_started_at": "2026-01-02T13:51:53Z",
						"update_at": "2026-01-02T14:41:54Z",
						"created_at": "2026-01-02T13:51:53Z",
						"duration": 3001
					},
					{
						"id": 20658851171,
						"status": "completed",
						"conclusion": "success",
						"actor": "tgummerer",
						"run_attempt": 1,
						"html_url": "https://github.com/pulumi/pulumi/actions/runs/20658851171/attempts/1",
						"jobs_url": "https://api.github.com/repos/pulumi/pulumi/actions/runs/20658851171/jobs",
						"logs_url": "https://api.github.com/repos/pulumi/pulumi/actions/runs/20658851171/logs",
						"run_started_at": "2026-01-02T13:26:55Z",
						"update_at": "2026-01-02T14:18:07Z",
						"created_at": "2026-01-02T13:26:55Z",
						"duration": 3072
					},
					{
						"id": 20658793345,
						"status": "completed",
						"conclusion": "success",
						"actor": "tgummerer",
						"run_attempt": 1,
						"html_url": "https://github.com/pulumi/pulumi/actions/runs/20658793345/attempts/1",
						"jobs_url": "https://api.github.com/repos/pulumi/pulumi/actions/runs/20658793345/jobs",
						"logs_url": "https://api.github.com/repos/pulumi/pulumi/actions/runs/20658793345/logs",
						"run_started_at": "2026-01-02T13:23:23Z",
						"update_at": "2026-01-02T14:14:15Z",
						"created_at": "2026-01-02T13:23:23Z",
						"duration": 3052
					}
				]
			}
		}
	},
	"workflow_jobs_stats_summary": []
}
